tap.py
unittest_TAP.py
bayeux-0.10.3.data/scripts/generate_TAP
bayeux-0.10.3.dist-info/top_level.txt
bayeux-0.10.3.dist-info/METADATA
bayeux-0.10.3.dist-info/DESCRIPTION.rst
bayeux-0.10.3.dist-info/metadata.json
bayeux-0.10.3.dist-info/WHEEL
bayeux-0.10.3.dist-info/RECORD
